README.rst
setup.py
etaprogress/__init__.py
etaprogress/eta.py
etaprogress/progress.py
etaprogress.egg-info/PKG-INFO
etaprogress.egg-info/SOURCES.txt
etaprogress.egg-info/dependency_links.txt
etaprogress.egg-info/top_level.txt
etaprogress.egg-info/zip-safe
etaprogress/components/__init__.py
etaprogress/components/bars.py
etaprogress/components/base_progress_bar.py
etaprogress/components/eta_conversions.py
etaprogress/components/misc.py
etaprogress/components/units.py